coffee/__init__.py
coffee/mqtt/__init__.py
coffee/mqtt/client.py
coffee/mqtt/pattern.py
coffee/mqtt/topic.py
coffee_mqtt-1.0.2.dist-info/LICENSE
coffee_mqtt-1.0.2.dist-info/METADATA
coffee_mqtt-1.0.2.dist-info/WHEEL
coffee_mqtt-1.0.2.dist-info/top_level.txt
coffee_mqtt-1.0.2.dist-info/RECORD
