Metadata-Version: 2.1
Name: coffee-mqtt
Version: 1.0.2
Summary: Python MQTT framework
Home-page: https://github.com/phocs/coffee-mqtt
Author: Alessio Volpe
Author-email: alessio.volpe@aol.com
License: MIT License Copyright (c) 2020 Alessio Volpe
Keywords: coffee
Platform: UNKNOWN
Classifier: License :: OSI Approved
Classifier: Natural Language :: English
Classifier: Programming Language :: Python :: 3
Classifier: Operating System :: OS Independent
Classifier: Topic :: Communications
Classifier: Topic :: Internet
Requires-Python: >=3.6
Requires-Dist: paho-mqtt (==1.5.0)
